zplogger/__init__.py
zplogger/logger.py
zplogger-0.1.2.dist-info/LICENSE
zplogger-0.1.2.dist-info/METADATA
zplogger-0.1.2.dist-info/WHEEL
zplogger-0.1.2.dist-info/top_level.txt
zplogger-0.1.2.dist-info/RECORD
