Metadata-Version: 2.1
Name: zplogger
Version: 0.1.2
Summary: ZPower Logger
Home-page: https://github.com/zjhiphop/logger
Author: zjhiphop
Author-email: zjhiphop@gmail.com
License: MIT Licence
Platform: any
Classifier: Programming Language :: Python :: 3
Classifier: License :: OSI Approved :: MIT License
Classifier: Operating System :: OS Independent
Requires-Dist: requests (>=2.21.0)
